multinear/__init__.py
multinear/main.py
multinear/api/__init__.py
multinear/api/router.py
multinear/api/schemas.py
multinear/cli/__init__.py
multinear/cli/main.py
multinear/cli/utils.py
multinear/cli/commands/__init__.py
multinear/cli/commands/details.py
multinear/cli/commands/export.py
multinear/cli/commands/init.py
multinear/cli/commands/recent.py
multinear/cli/commands/run.py
multinear/cli/commands/web.py
multinear/engine/__init__.py
multinear/engine/checklist.py
multinear/engine/custom.py
multinear/engine/evaluate.py
multinear/engine/list.py
multinear/engine/run.py
multinear/engine/run_group.py
multinear/engine/run_select.py
multinear/engine/storage.py
multinear/engine/utils.py
multinear/engine/weighted_score.py
multinear/frontend/.env.example
multinear/frontend/.gitignore
multinear/frontend/.npmrc
multinear/frontend/README.md
multinear/frontend/components.json
multinear/frontend/package-lock.json
multinear/frontend/package.json
multinear/frontend/postcss.config.js
multinear/frontend/svelte.config.js
multinear/frontend/tailwind.config.ts
multinear/frontend/tsconfig.json
multinear/frontend/vite.config.ts
multinear/frontend/build/favicon.ico
multinear/frontend/build/index.html
multinear/frontend/build/_app/env.js
multinear/frontend/build/_app/version.json
multinear/frontend/build/_app/immutable/assets/0.CetVtmRu.css
multinear/frontend/build/_app/immutable/assets/4.CQYZWOEE.css
multinear/frontend/build/_app/immutable/assets/7.BvmSFJDm.css
multinear/frontend/build/_app/immutable/assets/_layout.CetVtmRu.css
multinear/frontend/build/_app/immutable/assets/_page.BvmSFJDm.css
multinear/frontend/build/_app/immutable/assets/_page.CQYZWOEE.css
multinear/frontend/build/_app/immutable/assets/logo.o9F5wtRW.png
multinear/frontend/build/_app/immutable/chunks/ErrorDisplay.DZ0Gu5b_.js
multinear/frontend/build/_app/immutable/chunks/EvaluationResults.BAMCpLbq.js
multinear/frontend/build/_app/immutable/chunks/Loading.DkR_FJp9.js
multinear-0.1.8.dist-info/licenses/LICENSE
multinear-0.1.8.dist-info/METADATA
multinear-0.1.8.dist-info/WHEEL
multinear-0.1.8.dist-info/entry_points.txt
multinear-0.1.8.dist-info/top_level.txt
multinear-0.1.8.dist-info/RECORD
