Metadata-Version: 2.4
Name: multinear
Version: 0.1.8
Summary: Multinear platform
Home-page: https://github.com/multinear/multinear
Author: Dima Kuchin
Author-email: dima@mirable.io
Requires-Python: >=3.8
License-File: LICENSE
Requires-Dist: autoevals>=0.0.105
Requires-Dist: fastapi[standard]>=0.103
Requires-Dist: jinja2>=3.1.4
Requires-Dist: jsonpath-ng>=1.7.0
Requires-Dist: openai>=1.55.0
Requires-Dist: rich>=13.9.4
Requires-Dist: sqlalchemy>=2.0.36
Requires-Dist: tqdm>=4.67.0
Requires-Dist: uvicorn[standard]>=0.23
Dynamic: author
Dynamic: author-email
Dynamic: home-page
Dynamic: license-file
Dynamic: requires-python
